_atoti_core/__init__.py
_atoti_core/get_atoti_home.py
_atoti_core/get_installed_plugins.py
_atoti_core/java_option.py
_atoti_core/license_key_env_var_name.py
_atoti_core/license_key_location.py
_atoti_core/os_wise_unique_id.py
_atoti_core/plugin.py
_atoti_core/py.typed
atoti_core-0.9.12.dist-info/WHEEL
atoti_core-0.9.12.dist-info/METADATA
atoti_core-0.9.12.dist-info/RECORD
