Metadata-Version: 2.3
Name: atoti-core
Version: 0.9.12
Summary: Code required by both client and server Atoti packages
Author: ActiveViam
Author-email: ActiveViam <atoti-dev@activeviam.com>
Classifier: Development Status :: 4 - Beta
Classifier: License :: Free for non-commercial use
Classifier: Operating System :: OS Independent
Classifier: Programming Language :: Java
Classifier: Programming Language :: Python :: 3
Classifier: Typing :: Typed
Requires-Python: >=3.10
Project-URL: Homepage, https://www.atoti.io
Project-URL: Issues, https://github.com/atoti/atoti/issues
